[{"id":"1","isbn_number":"1133307280","custom_price":"0","real_price":"28.75","difference":"28.75"},{"id":"15","isbn_number":"1420089277","custom_price":"0","real_price":"43.00","difference":"43.00"},{"id":"17","isbn_number":"0060417501","custom_price":"0","real_price":"29.25","difference":"29.25"},{"id":"18","isbn_number":"0470847549","custom_price":"0","real_price":"32.75","difference":"32.75"},{"id":"19","isbn_number":"0205959490","custom_price":"100","real_price":"105.75","difference":"5.75"},{"id":"20","isbn_number":"0072977051","custom_price":"0","real_price":"34.25","difference":"34.25"},{"id":"22","isbn_number":"0393935183","custom_price":"0","real_price":"5.50","difference":"5.50"},{"id":"23","isbn_number":"0078023130","custom_price":"0","real_price":"23.50","difference":"23.50"},{"id":"25","isbn_number":"0393138488","custom_price":"0","real_price":"44.00","difference":"44.00"},{"id":"26","isbn_number":"0471802379","custom_price":"80","real_price":"84","difference":"4"}]